{
  "resource": {
    "id": "9f8cb86f-d933-4f88-8d18-177d377ec82b",
    "title": "114年8月翡翠水庫運轉資料"
  },
  "result": {
    "limit": 1000,
    "offset": 0,
    "count": 31,
    "results": [
      {
        "_id": 1,
        "_importdate": {
          "date": "2026-05-08 17:35:04.186658",
          "timezone_type": 3,
          "timezone": "Asia/Taipei"
        },
        "日期": "8月1日",
        "水庫名稱": "翡翠水庫",
        "翡翠水庫日平均水位/公尺": "161.97",
        "有效容量": "299.032",
        "集水區雨量": "2.8",
        "進水量": "1,760,384",
        "放流量合計": "2,352,384",
        "進流量減放流量/立方公尺": "-592,000",
        "南勢溪流量/立方公尺": "2,841,840",
        "南北勢溪合計原水量/立方公尺": "5,194,224"
      },
      {
        "_id": 2,
        "_importdate": {
          "date": "2026-05-08 17:35:04.193076",
          "timezone_type": 3,
          "timezone": "Asia/Taipei"
        },
        "日期": "8月2日",
        "水庫名稱": "翡翠水庫",
        "翡翠水庫日平均水位/公尺": "161.82",
        "有效容量": "297.81",
        "集水區雨量": "32.8",
        "進水量": "2,674,996",
        "放流量合計": "3,180,996",
        "進流量減放流量/立方公尺": "-506,000",
        "南勢溪流量/立方公尺": "3,161,160",
        "南北勢溪合計原水量/立方公尺": "6,342,156"
      },
      {
        "_id": 3,
        "_importdate": {
          "date": "2026-05-08 17:35:04.193831",
          "timezone_type": 3,
          "timezone": "Asia/Taipei"
        },
        "日期": "8月3日",
        "水庫名稱": "翡翠水庫",
        "翡翠水庫日平均水位/公尺": "161.86",
        "有效容量": "298.187",
        "集水區雨量": "28.9",
        "進水量": "4,528,036",
        "放流量合計": "3,177,036",
        "進流量減放流量/立方公尺": "1,351,000",
        "南勢溪流量/立方公尺": "3,300,120",
        "南北勢溪合計原水量/立方公尺": "6,477,156"
      },
      {
        "_id": 4,
        "_importdate": {
          "date": "2026-05-08 17:35:04.194365",
          "timezone_type": 3,
          "timezone": "Asia/Taipei"
        },
        "日期": "8月4日",
        "水庫名稱": "翡翠水庫",
        "翡翠水庫日平均水位/公尺": "162.03",
        "有效容量": "299.505",
        "集水區雨量": "0.6",
        "進水量": "3,344,128",
        "放流量合計": "3,175,128",
        "進流量減放流量/立方公尺": "169,000",
        "南勢溪流量/立方公尺": "3,294,720",
        "南北勢溪合計原水量/立方公尺": "6,469,848"
      },
      {
        "_id": 5,
        "_importdate": {
          "date": "2026-05-08 17:35:04.194885",
          "timezone_type": 3,
          "timezone": "Asia/Taipei"
        },
        "日期": "8月5日",
        "水庫名稱": "翡翠水庫",
        "翡翠水庫日平均水位/公尺": "162.06",
        "有效容量": "299.914",
        "集水區雨量": "52",
        "進水量": "5,370,512",
        "放流量合計": "3,169,512",
        "進流量減放流量/立方公尺": "2,201,000",
        "南勢溪流量/立方公尺": "4,291,200",
        "南北勢溪合計原水量/立方公尺": "7,460,712"
      },
      {
        "_id": 6,
        "_importdate": {
          "date": "2026-05-08 17:35:04.195357",
          "timezone_type": 3,
          "timezone": "Asia/Taipei"
        },
        "日期": "8月6日",
        "水庫名稱": "翡翠水庫",
        "翡翠水庫日平均水位/公尺": "162.32",
        "有效容量": "301.993",
        "集水區雨量": "0.1",
        "進水量": "3,737,224",
        "放流量合計": "3,313,224",
        "進流量減放流量/立方公尺": "424,000",
        "南勢溪流量/立方公尺": "3,491,280",
        "南北勢溪合計原水量/立方公尺": "6,804,504"
      },
      {
        "_id": 7,
        "_importdate": {
          "date": "2026-05-08 17:35:04.195816",
          "timezone_type": 3,
          "timezone": "Asia/Taipei"
        },
        "日期": "8月7日",
        "水庫名稱": "翡翠水庫",
        "翡翠水庫日平均水位/公尺": "162.27",
        "有效容量": "301.534",
        "集水區雨量": "0",
        "進水量": "2,354,580",
        "放流量合計": "3,371,580",
        "進流量減放流量/立方公尺": "-1,017,000",
        "南勢溪流量/立方公尺": "2,819,880",
        "南北勢溪合計原水量/立方公尺": "6,191,460"
      },
      {
        "_id": 8,
        "_importdate": {
          "date": "2026-05-08 17:35:04.196407",
          "timezone_type": 3,
          "timezone": "Asia/Taipei"
        },
        "日期": "8月8日",
        "水庫名稱": "翡翠水庫",
        "翡翠水庫日平均水位/公尺": "162.11",
        "有效容量": "300.16",
        "集水區雨量": "0",
        "進水量": "1,769,628",
        "放流量合計": "3,377,628",
        "進流量減放流量/立方公尺": "-1,608,000",
        "南勢溪流量/立方公尺": "2,473,920",
        "南北勢溪合計原水量/立方公尺": "5,851,548"
      },
      {
        "_id": 9,
        "_importdate": {
          "date": "2026-05-08 17:35:04.196927",
          "timezone_type": 3,
          "timezone": "Asia/Taipei"
        },
        "日期": "8月9日",
        "水庫名稱": "翡翠水庫",
        "翡翠水庫日平均水位/公尺": "161.9",
        "有效容量": "298.377",
        "集水區雨量": "0",
        "進水量": "1,376,348",
        "放流量合計": "3,234,348",
        "進流量減放流量/立方公尺": "-1,858,000",
        "南勢溪流量/立方公尺": "2,201,040",
        "南北勢溪合計原水量/立方公尺": "5,435,388"
      },
      {
        "_id": 10,
        "_importdate": {
          "date": "2026-05-08 17:35:04.197400",
          "timezone_type": 3,
          "timezone": "Asia/Taipei"
        },
        "日期": "8月10日",
        "水庫名稱": "翡翠水庫",
        "翡翠水庫日平均水位/公尺": "161.67",
        "有效容量": "296.489",
        "集水區雨量": "3.3",
        "進水量": "1,249,368",
        "放流量合計": "3,187,368",
        "進流量減放流量/立方公尺": "-1,938,000",
        "南勢溪流量/立方公尺": "1,996,560",
        "南北勢溪合計原水量/立方公尺": "5,183,928"
      },
      {
        "_id": 11,
        "_importdate": {
          "date": "2026-05-08 17:35:04.197897",
          "timezone_type": 3,
          "timezone": "Asia/Taipei"
        },
        "日期": "8月11日",
        "水庫名稱": "翡翠水庫",
        "翡翠水庫日平均水位/公尺": "161.32",
        "有效容量": "293.467",
        "集水區雨量": "4.9",
        "進水量": "1,350,996",
        "放流量合計": "4,710,996",
        "進流量減放流量/立方公尺": "-3,360,000",
        "南勢溪流量/立方公尺": "1,905,840",
        "南北勢溪合計原水量/立方公尺": "6,616,836"
      },
      {
        "_id": 12,
        "_importdate": {
          "date": "2026-05-08 17:35:04.198357",
          "timezone_type": 3,
          "timezone": "Asia/Taipei"
        },
        "日期": "8月12日",
        "水庫名稱": "翡翠水庫",
        "翡翠水庫日平均水位/公尺": "161.12",
        "有效容量": "291.799",
        "集水區雨量": "0.4",
        "進水量": "943,856",
        "放流量合計": "2,366,856",
        "進流量減放流量/立方公尺": "-1,423,000",
        "南勢溪流量/立方公尺": "1,774,080",
        "南北勢溪合計原水量/立方公尺": "4,140,936"
      },
      {
        "_id": 13,
        "_importdate": {
          "date": "2026-05-08 17:35:04.199020",
          "timezone_type": 3,
          "timezone": "Asia/Taipei"
        },
        "日期": "8月13日",
        "水庫名稱": "翡翠水庫",
        "翡翠水庫日平均水位/公尺": "161",
        "有效容量": "290.854",
        "集水區雨量": "27.3",
        "進水量": "1,781,380",
        "放流量合計": "2,365,380",
        "進流量減放流量/立方公尺": "-584,000",
        "南勢溪流量/立方公尺": "2,523,600",
        "南北勢溪合計原水量/立方公尺": "4,888,980"
      },
      {
        "_id": 14,
        "_importdate": {
          "date": "2026-05-08 17:35:04.199546",
          "timezone_type": 3,
          "timezone": "Asia/Taipei"
        },
        "日期": "8月14日",
        "水庫名稱": "翡翠水庫",
        "翡翠水庫日平均水位/公尺": "160.89",
        "有效容量": "289.897",
        "集水區雨量": "0.5",
        "進水量": "1,123,372",
        "放流量合計": "2,373,372",
        "進流量減放流量/立方公尺": "-1,250,000",
        "南勢溪流量/立方公尺": "2,534,400",
        "南北勢溪合計原水量/立方公尺": "4,907,772"
      },
      {
        "_id": 15,
        "_importdate": {
          "date": "2026-05-08 17:35:04.200336",
          "timezone_type": 3,
          "timezone": "Asia/Taipei"
        },
        "日期": "8月15日",
        "水庫名稱": "翡翠水庫",
        "翡翠水庫日平均水位/公尺": "160.73",
        "有效容量": "288.584",
        "集水區雨量": "0.3",
        "進水量": "961,524",
        "放流量合計": "2,374,524",
        "進流量減放流量/立方公尺": "-1,413,000",
        "南勢溪流量/立方公尺": "2,050,560",
        "南北勢溪合計原水量/立方公尺": "4,425,084"
      },
      {
        "_id": 16,
        "_importdate": {
          "date": "2026-05-08 17:35:04.200887",
          "timezone_type": 3,
          "timezone": "Asia/Taipei"
        },
        "日期": "8月16日",
        "水庫名稱": "翡翠水庫",
        "翡翠水庫日平均水位/公尺": "160.55",
        "有效容量": "287.058",
        "集水區雨量": "3.1",
        "進水量": "805,688",
        "放流量合計": "2,381,688",
        "進流量減放流量/立方公尺": "-1,576,000",
        "南勢溪流量/立方公尺": "1,815,120",
        "南北勢溪合計原水量/立方公尺": "4,196,808"
      },
      {
        "_id": 17,
        "_importdate": {
          "date": "2026-05-08 17:35:04.201556",
          "timezone_type": 3,
          "timezone": "Asia/Taipei"
        },
        "日期": "8月17日",
        "水庫名稱": "翡翠水庫",
        "翡翠水庫日平均水位/公尺": "160.35",
        "有效容量": "285.451",
        "集水區雨量": "0.1",
        "進水量": "730,020",
        "放流量合計": "2,383,020",
        "進流量減放流量/立方公尺": "-1,653,000",
        "南勢溪流量/立方公尺": "1,742,400",
        "南北勢溪合計原水量/立方公尺": "4,125,420"
      },
      {
        "_id": 18,
        "_importdate": {
          "date": "2026-05-08 17:35:04.202129",
          "timezone_type": 3,
          "timezone": "Asia/Taipei"
        },
        "日期": "8月18日",
        "水庫名稱": "翡翠水庫",
        "翡翠水庫日平均水位/公尺": "160.15",
        "有效容量": "283.778",
        "集水區雨量": "1.6",
        "進水量": "737,836",
        "放流量合計": "2,386,836",
        "進流量減放流量/立方公尺": "-1,649,000",
        "南勢溪流量/立方公尺": "1,667,520",
        "南北勢溪合計原水量/立方公尺": "4,054,356"
      },
      {
        "_id": 19,
        "_importdate": {
          "date": "2026-05-08 17:35:04.202624",
          "timezone_type": 3,
          "timezone": "Asia/Taipei"
        },
        "日期": "8月19日",
        "水庫名稱": "翡翠水庫",
        "翡翠水庫日平均水位/公尺": "159.96",
        "有效容量": "282.198",
        "集水區雨量": "5.9",
        "進水量": "831,368",
        "放流量合計": "2,395,368",
        "進流量減放流量/立方公尺": "-1,564,000",
        "南勢溪流量/立方公尺": "1,621,440",
        "南北勢溪合計原水量/立方公尺": "4,016,808"
      },
      {
        "_id": 20,
        "_importdate": {
          "date": "2026-05-08 17:35:04.203078",
          "timezone_type": 3,
          "timezone": "Asia/Taipei"
        },
        "日期": "8月20日",
        "水庫名稱": "翡翠水庫",
        "翡翠水庫日平均水位/公尺": "159.76",
        "有效容量": "280.546",
        "集水區雨量": "1.4",
        "進水量": "674,780",
        "放流量合計": "2,397,780",
        "進流量減放流量/立方公尺": "-1,723,000",
        "南勢溪流量/立方公尺": "1,508,400",
        "南北勢溪合計原水量/立方公尺": "3,906,180"
      },
      {
        "_id": 21,
        "_importdate": {
          "date": "2026-05-08 17:35:04.203539",
          "timezone_type": 3,
          "timezone": "Asia/Taipei"
        },
        "日期": "8月21日",
        "水庫名稱": "翡翠水庫",
        "翡翠水庫日平均水位/公尺": "159.55",
        "有效容量": "278.84",
        "集水區雨量": "0.3",
        "進水量": "545,332",
        "放流量合計": "1,855,332",
        "進流量減放流量/立方公尺": "-1,310,000",
        "南勢溪流量/立方公尺": "1,499,040",
        "南北勢溪合計原水量/立方公尺": "3,354,372"
      },
      {
        "_id": 22,
        "_importdate": {
          "date": "2026-05-08 17:35:04.204219",
          "timezone_type": 3,
          "timezone": "Asia/Taipei"
        },
        "日期": "8月22日",
        "水庫名稱": "翡翠水庫",
        "翡翠水庫日平均水位/公尺": "159.39",
        "有效容量": "277.545",
        "集水區雨量": "0",
        "進水量": "548,980",
        "放流量合計": "1,855,980",
        "進流量減放流量/立方公尺": "-1,307,000",
        "南勢溪流量/立方公尺": "1,454,400",
        "南北勢溪合計原水量/立方公尺": "3,310,380"
      },
      {
        "_id": 23,
        "_importdate": {
          "date": "2026-05-08 17:35:04.204704",
          "timezone_type": 3,
          "timezone": "Asia/Taipei"
        },
        "日期": "8月23日",
        "水庫名稱": "翡翠水庫",
        "翡翠水庫日平均水位/公尺": "159.22",
        "有效容量": "276.184",
        "集水區雨量": "0",
        "進水量": "473,220",
        "放流量合計": "1,859,220",
        "進流量減放流量/立方公尺": "-1,386,000",
        "南勢溪流量/立方公尺": "1,356,480",
        "南北勢溪合計原水量/立方公尺": "3,215,700"
      },
      {
        "_id": 24,
        "_importdate": {
          "date": "2026-05-08 17:35:04.205161",
          "timezone_type": 3,
          "timezone": "Asia/Taipei"
        },
        "日期": "8月24日",
        "水庫名稱": "翡翠水庫",
        "翡翠水庫日平均水位/公尺": "159.05",
        "有效容量": "274.799",
        "集水區雨量": "0",
        "進水量": "400,208",
        "放流量合計": "1,862,208",
        "進流量減放流量/立方公尺": "-1,462,000",
        "南勢溪流量/立方公尺": "1,304,640",
        "南北勢溪合計原水量/立方公尺": "3,166,848"
      },
      {
        "_id": 25,
        "_importdate": {
          "date": "2026-05-08 17:35:04.205654",
          "timezone_type": 3,
          "timezone": "Asia/Taipei"
        },
        "日期": "8月25日",
        "水庫名稱": "翡翠水庫",
        "翡翠水庫日平均水位/公尺": "158.88",
        "有效容量": "273.388",
        "集水區雨量": "0",
        "進水量": "489,340",
        "放流量合計": "1,865,340",
        "進流量減放流量/立方公尺": "-1,376,000",
        "南勢溪流量/立方公尺": "1,256,400",
        "南北勢溪合計原水量/立方公尺": "3,121,740"
      },
      {
        "_id": 26,
        "_importdate": {
          "date": "2026-05-08 17:35:04.206219",
          "timezone_type": 3,
          "timezone": "Asia/Taipei"
        },
        "日期": "8月26日",
        "水庫名稱": "翡翠水庫",
        "翡翠水庫日平均水位/公尺": "158.7",
        "有效容量": "271.932",
        "集水區雨量": "0",
        "進水量": "334,580",
        "放流量合計": "1,868,580",
        "進流量減放流量/立方公尺": "-1,534,000",
        "南勢溪流量/立方公尺": "1,195,200",
        "南北勢溪合計原水量/立方公尺": "3,063,780"
      },
      {
        "_id": 27,
        "_importdate": {
          "date": "2026-05-08 17:35:04.206721",
          "timezone_type": 3,
          "timezone": "Asia/Taipei"
        },
        "日期": "8月27日",
        "水庫名稱": "翡翠水庫",
        "翡翠水庫日平均水位/公尺": "158.52",
        "有效容量": "270.453",
        "集水區雨量": "0.6",
        "進水量": "424,936",
        "放流量合計": "1,872,936",
        "進流量減放流量/立方公尺": "-1,448,000",
        "南勢溪流量/立方公尺": "1,152,000",
        "南北勢溪合計原水量/立方公尺": "3,024,936"
      },
      {
        "_id": 28,
        "_importdate": {
          "date": "2026-05-08 17:35:04.207182",
          "timezone_type": 3,
          "timezone": "Asia/Taipei"
        },
        "日期": "8月28日",
        "水庫名稱": "翡翠水庫",
        "翡翠水庫日平均水位/公尺": "158.34",
        "有效容量": "268.988",
        "集水區雨量": "0",
        "進水量": "431,528",
        "放流量合計": "1,875,528",
        "進流量減放流量/立方公尺": "-1,444,000",
        "南勢溪流量/立方公尺": "1,097,280",
        "南北勢溪合計原水量/立方公尺": "2,972,808"
      },
      {
        "_id": 29,
        "_importdate": {
          "date": "2026-05-08 17:35:04.207703",
          "timezone_type": 3,
          "timezone": "Asia/Taipei"
        },
        "日期": "8月29日",
        "水庫名稱": "翡翠水庫",
        "翡翠水庫日平均水位/公尺": "158.15",
        "有效容量": "267.482",
        "集水區雨量": "0",
        "進水量": "280,128",
        "放流量合計": "1,879,128",
        "進流量減放流量/立方公尺": "-1,599,000",
        "南勢溪流量/立方公尺": "1,082,160",
        "南北勢溪合計原水量/立方公尺": "2,961,288"
      },
      {
        "_id": 30,
        "_importdate": {
          "date": "2026-05-08 17:35:04.208167",
          "timezone_type": 3,
          "timezone": "Asia/Taipei"
        },
        "日期": "8月30日",
        "水庫名稱": "翡翠水庫",
        "翡翠水庫日平均水位/公尺": "157.95",
        "有效容量": "265.928",
        "集水區雨量": "0",
        "進水量": "372,052",
        "放流量合計": "1,883,052",
        "進流量減放流量/立方公尺": "-1,511,000",
        "南勢溪流量/立方公尺": "1,044,000",
        "南北勢溪合計原水量/立方公尺": "2,927,052"
      },
      {
        "_id": 31,
        "_importdate": {
          "date": "2026-05-08 17:35:04.208700",
          "timezone_type": 3,
          "timezone": "Asia/Taipei"
        },
        "日期": "8月31日",
        "水庫名稱": "翡翠水庫",
        "翡翠水庫日平均水位/公尺": "157.76",
        "有效容量": "264.408",
        "集水區雨量": "0",
        "進水量": "381,292",
        "放流量合計": "1,886,292",
        "進流量減放流量/立方公尺": "-1,505,000",
        "南勢溪流量/立方公尺": "1,014,480",
        "南北勢溪合計原水量/立方公尺": "2,900,772"
      }
    ]
  },
  "sourceEnvelope": {
    "result": {
      "limit": 1000,
      "offset": 0,
      "count": 31,
      "sort": "",
      "results": [
        {
          "_id": 1,
          "_importdate": {
            "date": "2026-05-08 17:35:04.186658",
            "timezone_type": 3,
            "timezone": "Asia/Taipei"
          },
          "日期": "8月1日",
          "水庫名稱": "翡翠水庫",
          "翡翠水庫日平均水位/公尺": "161.97",
          "有效容量": "299.032",
          "集水區雨量": "2.8",
          "進水量": "1,760,384",
          "放流量合計": "2,352,384",
          "進流量減放流量/立方公尺": "-592,000",
          "南勢溪流量/立方公尺": "2,841,840",
          "南北勢溪合計原水量/立方公尺": "5,194,224"
        },
        {
          "_id": 2,
          "_importdate": {
            "date": "2026-05-08 17:35:04.193076",
            "timezone_type": 3,
            "timezone": "Asia/Taipei"
          },
          "日期": "8月2日",
          "水庫名稱": "翡翠水庫",
          "翡翠水庫日平均水位/公尺": "161.82",
          "有效容量": "297.81",
          "集水區雨量": "32.8",
          "進水量": "2,674,996",
          "放流量合計": "3,180,996",
          "進流量減放流量/立方公尺": "-506,000",
          "南勢溪流量/立方公尺": "3,161,160",
          "南北勢溪合計原水量/立方公尺": "6,342,156"
        },
        {
          "_id": 3,
          "_importdate": {
            "date": "2026-05-08 17:35:04.193831",
            "timezone_type": 3,
            "timezone": "Asia/Taipei"
          },
          "日期": "8月3日",
          "水庫名稱": "翡翠水庫",
          "翡翠水庫日平均水位/公尺": "161.86",
          "有效容量": "298.187",
          "集水區雨量": "28.9",
          "進水量": "4,528,036",
          "放流量合計": "3,177,036",
          "進流量減放流量/立方公尺": "1,351,000",
          "南勢溪流量/立方公尺": "3,300,120",
          "南北勢溪合計原水量/立方公尺": "6,477,156"
        },
        {
          "_id": 4,
          "_importdate": {
            "date": "2026-05-08 17:35:04.194365",
            "timezone_type": 3,
            "timezone": "Asia/Taipei"
          },
          "日期": "8月4日",
          "水庫名稱": "翡翠水庫",
          "翡翠水庫日平均水位/公尺": "162.03",
          "有效容量": "299.505",
          "集水區雨量": "0.6",
          "進水量": "3,344,128",
          "放流量合計": "3,175,128",
          "進流量減放流量/立方公尺": "169,000",
          "南勢溪流量/立方公尺": "3,294,720",
          "南北勢溪合計原水量/立方公尺": "6,469,848"
        },
        {
          "_id": 5,
          "_importdate": {
            "date": "2026-05-08 17:35:04.194885",
            "timezone_type": 3,
            "timezone": "Asia/Taipei"
          },
          "日期": "8月5日",
          "水庫名稱": "翡翠水庫",
          "翡翠水庫日平均水位/公尺": "162.06",
          "有效容量": "299.914",
          "集水區雨量": "52",
          "進水量": "5,370,512",
          "放流量合計": "3,169,512",
          "進流量減放流量/立方公尺": "2,201,000",
          "南勢溪流量/立方公尺": "4,291,200",
          "南北勢溪合計原水量/立方公尺": "7,460,712"
        },
        {
          "_id": 6,
          "_importdate": {
            "date": "2026-05-08 17:35:04.195357",
            "timezone_type": 3,
            "timezone": "Asia/Taipei"
          },
          "日期": "8月6日",
          "水庫名稱": "翡翠水庫",
          "翡翠水庫日平均水位/公尺": "162.32",
          "有效容量": "301.993",
          "集水區雨量": "0.1",
          "進水量": "3,737,224",
          "放流量合計": "3,313,224",
          "進流量減放流量/立方公尺": "424,000",
          "南勢溪流量/立方公尺": "3,491,280",
          "南北勢溪合計原水量/立方公尺": "6,804,504"
        },
        {
          "_id": 7,
          "_importdate": {
            "date": "2026-05-08 17:35:04.195816",
            "timezone_type": 3,
            "timezone": "Asia/Taipei"
          },
          "日期": "8月7日",
          "水庫名稱": "翡翠水庫",
          "翡翠水庫日平均水位/公尺": "162.27",
          "有效容量": "301.534",
          "集水區雨量": "0",
          "進水量": "2,354,580",
          "放流量合計": "3,371,580",
          "進流量減放流量/立方公尺": "-1,017,000",
          "南勢溪流量/立方公尺": "2,819,880",
          "南北勢溪合計原水量/立方公尺": "6,191,460"
        },
        {
          "_id": 8,
          "_importdate": {
            "date": "2026-05-08 17:35:04.196407",
            "timezone_type": 3,
            "timezone": "Asia/Taipei"
          },
          "日期": "8月8日",
          "水庫名稱": "翡翠水庫",
          "翡翠水庫日平均水位/公尺": "162.11",
          "有效容量": "300.16",
          "集水區雨量": "0",
          "進水量": "1,769,628",
          "放流量合計": "3,377,628",
          "進流量減放流量/立方公尺": "-1,608,000",
          "南勢溪流量/立方公尺": "2,473,920",
          "南北勢溪合計原水量/立方公尺": "5,851,548"
        },
        {
          "_id": 9,
          "_importdate": {
            "date": "2026-05-08 17:35:04.196927",
            "timezone_type": 3,
            "timezone": "Asia/Taipei"
          },
          "日期": "8月9日",
          "水庫名稱": "翡翠水庫",
          "翡翠水庫日平均水位/公尺": "161.9",
          "有效容量": "298.377",
          "集水區雨量": "0",
          "進水量": "1,376,348",
          "放流量合計": "3,234,348",
          "進流量減放流量/立方公尺": "-1,858,000",
          "南勢溪流量/立方公尺": "2,201,040",
          "南北勢溪合計原水量/立方公尺": "5,435,388"
        },
        {
          "_id": 10,
          "_importdate": {
            "date": "2026-05-08 17:35:04.197400",
            "timezone_type": 3,
            "timezone": "Asia/Taipei"
          },
          "日期": "8月10日",
          "水庫名稱": "翡翠水庫",
          "翡翠水庫日平均水位/公尺": "161.67",
          "有效容量": "296.489",
          "集水區雨量": "3.3",
          "進水量": "1,249,368",
          "放流量合計": "3,187,368",
          "進流量減放流量/立方公尺": "-1,938,000",
          "南勢溪流量/立方公尺": "1,996,560",
          "南北勢溪合計原水量/立方公尺": "5,183,928"
        },
        {
          "_id": 11,
          "_importdate": {
            "date": "2026-05-08 17:35:04.197897",
            "timezone_type": 3,
            "timezone": "Asia/Taipei"
          },
          "日期": "8月11日",
          "水庫名稱": "翡翠水庫",
          "翡翠水庫日平均水位/公尺": "161.32",
          "有效容量": "293.467",
          "集水區雨量": "4.9",
          "進水量": "1,350,996",
          "放流量合計": "4,710,996",
          "進流量減放流量/立方公尺": "-3,360,000",
          "南勢溪流量/立方公尺": "1,905,840",
          "南北勢溪合計原水量/立方公尺": "6,616,836"
        },
        {
          "_id": 12,
          "_importdate": {
            "date": "2026-05-08 17:35:04.198357",
            "timezone_type": 3,
            "timezone": "Asia/Taipei"
          },
          "日期": "8月12日",
          "水庫名稱": "翡翠水庫",
          "翡翠水庫日平均水位/公尺": "161.12",
          "有效容量": "291.799",
          "集水區雨量": "0.4",
          "進水量": "943,856",
          "放流量合計": "2,366,856",
          "進流量減放流量/立方公尺": "-1,423,000",
          "南勢溪流量/立方公尺": "1,774,080",
          "南北勢溪合計原水量/立方公尺": "4,140,936"
        },
        {
          "_id": 13,
          "_importdate": {
            "date": "2026-05-08 17:35:04.199020",
            "timezone_type": 3,
            "timezone": "Asia/Taipei"
          },
          "日期": "8月13日",
          "水庫名稱": "翡翠水庫",
          "翡翠水庫日平均水位/公尺": "161",
          "有效容量": "290.854",
          "集水區雨量": "27.3",
          "進水量": "1,781,380",
          "放流量合計": "2,365,380",
          "進流量減放流量/立方公尺": "-584,000",
          "南勢溪流量/立方公尺": "2,523,600",
          "南北勢溪合計原水量/立方公尺": "4,888,980"
        },
        {
          "_id": 14,
          "_importdate": {
            "date": "2026-05-08 17:35:04.199546",
            "timezone_type": 3,
            "timezone": "Asia/Taipei"
          },
          "日期": "8月14日",
          "水庫名稱": "翡翠水庫",
          "翡翠水庫日平均水位/公尺": "160.89",
          "有效容量": "289.897",
          "集水區雨量": "0.5",
          "進水量": "1,123,372",
          "放流量合計": "2,373,372",
          "進流量減放流量/立方公尺": "-1,250,000",
          "南勢溪流量/立方公尺": "2,534,400",
          "南北勢溪合計原水量/立方公尺": "4,907,772"
        },
        {
          "_id": 15,
          "_importdate": {
            "date": "2026-05-08 17:35:04.200336",
            "timezone_type": 3,
            "timezone": "Asia/Taipei"
          },
          "日期": "8月15日",
          "水庫名稱": "翡翠水庫",
          "翡翠水庫日平均水位/公尺": "160.73",
          "有效容量": "288.584",
          "集水區雨量": "0.3",
          "進水量": "961,524",
          "放流量合計": "2,374,524",
          "進流量減放流量/立方公尺": "-1,413,000",
          "南勢溪流量/立方公尺": "2,050,560",
          "南北勢溪合計原水量/立方公尺": "4,425,084"
        },
        {
          "_id": 16,
          "_importdate": {
            "date": "2026-05-08 17:35:04.200887",
            "timezone_type": 3,
            "timezone": "Asia/Taipei"
          },
          "日期": "8月16日",
          "水庫名稱": "翡翠水庫",
          "翡翠水庫日平均水位/公尺": "160.55",
          "有效容量": "287.058",
          "集水區雨量": "3.1",
          "進水量": "805,688",
          "放流量合計": "2,381,688",
          "進流量減放流量/立方公尺": "-1,576,000",
          "南勢溪流量/立方公尺": "1,815,120",
          "南北勢溪合計原水量/立方公尺": "4,196,808"
        },
        {
          "_id": 17,
          "_importdate": {
            "date": "2026-05-08 17:35:04.201556",
            "timezone_type": 3,
            "timezone": "Asia/Taipei"
          },
          "日期": "8月17日",
          "水庫名稱": "翡翠水庫",
          "翡翠水庫日平均水位/公尺": "160.35",
          "有效容量": "285.451",
          "集水區雨量": "0.1",
          "進水量": "730,020",
          "放流量合計": "2,383,020",
          "進流量減放流量/立方公尺": "-1,653,000",
          "南勢溪流量/立方公尺": "1,742,400",
          "南北勢溪合計原水量/立方公尺": "4,125,420"
        },
        {
          "_id": 18,
          "_importdate": {
            "date": "2026-05-08 17:35:04.202129",
            "timezone_type": 3,
            "timezone": "Asia/Taipei"
          },
          "日期": "8月18日",
          "水庫名稱": "翡翠水庫",
          "翡翠水庫日平均水位/公尺": "160.15",
          "有效容量": "283.778",
          "集水區雨量": "1.6",
          "進水量": "737,836",
          "放流量合計": "2,386,836",
          "進流量減放流量/立方公尺": "-1,649,000",
          "南勢溪流量/立方公尺": "1,667,520",
          "南北勢溪合計原水量/立方公尺": "4,054,356"
        },
        {
          "_id": 19,
          "_importdate": {
            "date": "2026-05-08 17:35:04.202624",
            "timezone_type": 3,
            "timezone": "Asia/Taipei"
          },
          "日期": "8月19日",
          "水庫名稱": "翡翠水庫",
          "翡翠水庫日平均水位/公尺": "159.96",
          "有效容量": "282.198",
          "集水區雨量": "5.9",
          "進水量": "831,368",
          "放流量合計": "2,395,368",
          "進流量減放流量/立方公尺": "-1,564,000",
          "南勢溪流量/立方公尺": "1,621,440",
          "南北勢溪合計原水量/立方公尺": "4,016,808"
        },
        {
          "_id": 20,
          "_importdate": {
            "date": "2026-05-08 17:35:04.203078",
            "timezone_type": 3,
            "timezone": "Asia/Taipei"
          },
          "日期": "8月20日",
          "水庫名稱": "翡翠水庫",
          "翡翠水庫日平均水位/公尺": "159.76",
          "有效容量": "280.546",
          "集水區雨量": "1.4",
          "進水量": "674,780",
          "放流量合計": "2,397,780",
          "進流量減放流量/立方公尺": "-1,723,000",
          "南勢溪流量/立方公尺": "1,508,400",
          "南北勢溪合計原水量/立方公尺": "3,906,180"
        },
        {
          "_id": 21,
          "_importdate": {
            "date": "2026-05-08 17:35:04.203539",
            "timezone_type": 3,
            "timezone": "Asia/Taipei"
          },
          "日期": "8月21日",
          "水庫名稱": "翡翠水庫",
          "翡翠水庫日平均水位/公尺": "159.55",
          "有效容量": "278.84",
          "集水區雨量": "0.3",
          "進水量": "545,332",
          "放流量合計": "1,855,332",
          "進流量減放流量/立方公尺": "-1,310,000",
          "南勢溪流量/立方公尺": "1,499,040",
          "南北勢溪合計原水量/立方公尺": "3,354,372"
        },
        {
          "_id": 22,
          "_importdate": {
            "date": "2026-05-08 17:35:04.204219",
            "timezone_type": 3,
            "timezone": "Asia/Taipei"
          },
          "日期": "8月22日",
          "水庫名稱": "翡翠水庫",
          "翡翠水庫日平均水位/公尺": "159.39",
          "有效容量": "277.545",
          "集水區雨量": "0",
          "進水量": "548,980",
          "放流量合計": "1,855,980",
          "進流量減放流量/立方公尺": "-1,307,000",
          "南勢溪流量/立方公尺": "1,454,400",
          "南北勢溪合計原水量/立方公尺": "3,310,380"
        },
        {
          "_id": 23,
          "_importdate": {
            "date": "2026-05-08 17:35:04.204704",
            "timezone_type": 3,
            "timezone": "Asia/Taipei"
          },
          "日期": "8月23日",
          "水庫名稱": "翡翠水庫",
          "翡翠水庫日平均水位/公尺": "159.22",
          "有效容量": "276.184",
          "集水區雨量": "0",
          "進水量": "473,220",
          "放流量合計": "1,859,220",
          "進流量減放流量/立方公尺": "-1,386,000",
          "南勢溪流量/立方公尺": "1,356,480",
          "南北勢溪合計原水量/立方公尺": "3,215,700"
        },
        {
          "_id": 24,
          "_importdate": {
            "date": "2026-05-08 17:35:04.205161",
            "timezone_type": 3,
            "timezone": "Asia/Taipei"
          },
          "日期": "8月24日",
          "水庫名稱": "翡翠水庫",
          "翡翠水庫日平均水位/公尺": "159.05",
          "有效容量": "274.799",
          "集水區雨量": "0",
          "進水量": "400,208",
          "放流量合計": "1,862,208",
          "進流量減放流量/立方公尺": "-1,462,000",
          "南勢溪流量/立方公尺": "1,304,640",
          "南北勢溪合計原水量/立方公尺": "3,166,848"
        },
        {
          "_id": 25,
          "_importdate": {
            "date": "2026-05-08 17:35:04.205654",
            "timezone_type": 3,
            "timezone": "Asia/Taipei"
          },
          "日期": "8月25日",
          "水庫名稱": "翡翠水庫",
          "翡翠水庫日平均水位/公尺": "158.88",
          "有效容量": "273.388",
          "集水區雨量": "0",
          "進水量": "489,340",
          "放流量合計": "1,865,340",
          "進流量減放流量/立方公尺": "-1,376,000",
          "南勢溪流量/立方公尺": "1,256,400",
          "南北勢溪合計原水量/立方公尺": "3,121,740"
        },
        {
          "_id": 26,
          "_importdate": {
            "date": "2026-05-08 17:35:04.206219",
            "timezone_type": 3,
            "timezone": "Asia/Taipei"
          },
          "日期": "8月26日",
          "水庫名稱": "翡翠水庫",
          "翡翠水庫日平均水位/公尺": "158.7",
          "有效容量": "271.932",
          "集水區雨量": "0",
          "進水量": "334,580",
          "放流量合計": "1,868,580",
          "進流量減放流量/立方公尺": "-1,534,000",
          "南勢溪流量/立方公尺": "1,195,200",
          "南北勢溪合計原水量/立方公尺": "3,063,780"
        },
        {
          "_id": 27,
          "_importdate": {
            "date": "2026-05-08 17:35:04.206721",
            "timezone_type": 3,
            "timezone": "Asia/Taipei"
          },
          "日期": "8月27日",
          "水庫名稱": "翡翠水庫",
          "翡翠水庫日平均水位/公尺": "158.52",
          "有效容量": "270.453",
          "集水區雨量": "0.6",
          "進水量": "424,936",
          "放流量合計": "1,872,936",
          "進流量減放流量/立方公尺": "-1,448,000",
          "南勢溪流量/立方公尺": "1,152,000",
          "南北勢溪合計原水量/立方公尺": "3,024,936"
        },
        {
          "_id": 28,
          "_importdate": {
            "date": "2026-05-08 17:35:04.207182",
            "timezone_type": 3,
            "timezone": "Asia/Taipei"
          },
          "日期": "8月28日",
          "水庫名稱": "翡翠水庫",
          "翡翠水庫日平均水位/公尺": "158.34",
          "有效容量": "268.988",
          "集水區雨量": "0",
          "進水量": "431,528",
          "放流量合計": "1,875,528",
          "進流量減放流量/立方公尺": "-1,444,000",
          "南勢溪流量/立方公尺": "1,097,280",
          "南北勢溪合計原水量/立方公尺": "2,972,808"
        },
        {
          "_id": 29,
          "_importdate": {
            "date": "2026-05-08 17:35:04.207703",
            "timezone_type": 3,
            "timezone": "Asia/Taipei"
          },
          "日期": "8月29日",
          "水庫名稱": "翡翠水庫",
          "翡翠水庫日平均水位/公尺": "158.15",
          "有效容量": "267.482",
          "集水區雨量": "0",
          "進水量": "280,128",
          "放流量合計": "1,879,128",
          "進流量減放流量/立方公尺": "-1,599,000",
          "南勢溪流量/立方公尺": "1,082,160",
          "南北勢溪合計原水量/立方公尺": "2,961,288"
        },
        {
          "_id": 30,
          "_importdate": {
            "date": "2026-05-08 17:35:04.208167",
            "timezone_type": 3,
            "timezone": "Asia/Taipei"
          },
          "日期": "8月30日",
          "水庫名稱": "翡翠水庫",
          "翡翠水庫日平均水位/公尺": "157.95",
          "有效容量": "265.928",
          "集水區雨量": "0",
          "進水量": "372,052",
          "放流量合計": "1,883,052",
          "進流量減放流量/立方公尺": "-1,511,000",
          "南勢溪流量/立方公尺": "1,044,000",
          "南北勢溪合計原水量/立方公尺": "2,927,052"
        },
        {
          "_id": 31,
          "_importdate": {
            "date": "2026-05-08 17:35:04.208700",
            "timezone_type": 3,
            "timezone": "Asia/Taipei"
          },
          "日期": "8月31日",
          "水庫名稱": "翡翠水庫",
          "翡翠水庫日平均水位/公尺": "157.76",
          "有效容量": "264.408",
          "集水區雨量": "0",
          "進水量": "381,292",
          "放流量合計": "1,886,292",
          "進流量減放流量/立方公尺": "-1,505,000",
          "南勢溪流量/立方公尺": "1,014,480",
          "南北勢溪合計原水量/立方公尺": "2,900,772"
        }
      ]
    }
  }
}
