{
  "resource": {
    "id": "f31113ca-14e9-417d-9801-343ee672be3e",
    "title": "106年10月水庫運轉資料"
  },
  "result": {
    "limit": 1000,
    "offset": 0,
    "count": 31,
    "results": [
      {
        "_id": 1,
        "_importdate": {
          "date": "2026-05-08 17:34:56.076394",
          "timezone_type": 3,
          "timezone": "Asia/Taipei"
        },
        "日期": "10月1日",
        "翡翠水庫日平均水位/公尺": "156.37",
        "水庫有效蓄水量/百萬立方公尺": "219.7",
        "集水區平均雨量/毫米": "0.5",
        "水庫進流量/立方公尺": "1,015,180",
        "水庫放流量/立方公尺": "1,926,180",
        "進流量減放流量/立方公尺": "-911,000",
        "南勢溪流量/立方公尺": "1,200,960",
        "南北勢溪合計原水量/立方公尺": "3,127,140"
      },
      {
        "_id": 2,
        "_importdate": {
          "date": "2026-05-08 17:34:56.085106",
          "timezone_type": 3,
          "timezone": "Asia/Taipei"
        },
        "日期": "10月2日",
        "翡翠水庫日平均水位/公尺": "156.22",
        "水庫有效蓄水量/百萬立方公尺": "218.59",
        "集水區平均雨量/毫米": "0",
        "水庫進流量/立方公尺": "739,560",
        "水庫放流量/立方公尺": "1,951,560",
        "進流量減放流量/立方公尺": "-1,212,000",
        "南勢溪流量/立方公尺": "1,127,520",
        "南北勢溪合計原水量/立方公尺": "3,079,080"
      },
      {
        "_id": 3,
        "_importdate": {
          "date": "2026-05-08 17:34:56.085696",
          "timezone_type": 3,
          "timezone": "Asia/Taipei"
        },
        "日期": "10月3日",
        "翡翠水庫日平均水位/公尺": "156.05",
        "水庫有效蓄水量/百萬立方公尺": "217.257",
        "集水區平均雨量/毫米": "8.5",
        "水庫進流量/立方公尺": "664,992",
        "水庫放流量/立方公尺": "2,248,992",
        "進流量減放流量/立方公尺": "-1,584,000",
        "南勢溪流量/立方公尺": "1,092,240",
        "南北勢溪合計原水量/立方公尺": "3,341,232"
      },
      {
        "_id": 4,
        "_importdate": {
          "date": "2026-05-08 17:34:56.086217",
          "timezone_type": 3,
          "timezone": "Asia/Taipei"
        },
        "日期": "10月4日",
        "翡翠水庫日平均水位/公尺": "155.89",
        "水庫有效蓄水量/百萬立方公尺": "216.108",
        "集水區平均雨量/毫米": "32.6",
        "水庫進流量/立方公尺": "1,152,344",
        "水庫放流量/立方公尺": "1,528,344",
        "進流量減放流量/立方公尺": "-376,000",
        "南勢溪流量/立方公尺": "1,503,360",
        "南北勢溪合計原水量/立方公尺": "3,031,704"
      },
      {
        "_id": 5,
        "_importdate": {
          "date": "2026-05-08 17:34:56.086691",
          "timezone_type": 3,
          "timezone": "Asia/Taipei"
        },
        "日期": "10月5日",
        "翡翠水庫日平均水位/公尺": "155.9",
        "水庫有效蓄水量/百萬立方公尺": "216.186",
        "集水區平均雨量/毫米": "3.9",
        "水庫進流量/立方公尺": "1,830,064",
        "水庫放流量/立方公尺": "1,529,064",
        "進流量減放流量/立方公尺": "301,000",
        "南勢溪流量/立方公尺": "1,771,200",
        "南北勢溪合計原水量/立方公尺": "3,300,264"
      },
      {
        "_id": 6,
        "_importdate": {
          "date": "2026-05-08 17:34:56.087183",
          "timezone_type": 3,
          "timezone": "Asia/Taipei"
        },
        "日期": "10月6日",
        "翡翠水庫日平均水位/公尺": "155.9",
        "水庫有效蓄水量/百萬立方公尺": "216.18",
        "集水區平均雨量/毫米": "18.1",
        "水庫進流量/立方公尺": "1,380,252",
        "水庫放流量/立方公尺": "1,530,252",
        "進流量減放流量/立方公尺": "-150,000",
        "南勢溪流量/立方公尺": "1,743,120",
        "南北勢溪合計原水量/立方公尺": "3,273,372"
      },
      {
        "_id": 7,
        "_importdate": {
          "date": "2026-05-08 17:34:56.087747",
          "timezone_type": 3,
          "timezone": "Asia/Taipei"
        },
        "日期": "10月7日",
        "翡翠水庫日平均水位/公尺": "156.04",
        "水庫有效蓄水量/百萬立方公尺": "217.323",
        "集水區平均雨量/毫米": "12.7",
        "水庫進流量/立方公尺": "3,716,452",
        "水庫放流量/立方公尺": "1,528,452",
        "進流量減放流量/立方公尺": "2,188,000",
        "南勢溪流量/立方公尺": "3,348,360",
        "南北勢溪合計原水量/立方公尺": "4,876,812"
      },
      {
        "_id": 8,
        "_importdate": {
          "date": "2026-05-08 17:34:56.088234",
          "timezone_type": 3,
          "timezone": "Asia/Taipei"
        },
        "日期": "10月8日",
        "翡翠水庫日平均水位/公尺": "156.24",
        "水庫有效蓄水量/百萬立方公尺": "218.782",
        "集水區平均雨量/毫米": "10.7",
        "水庫進流量/立方公尺": "2,288,820",
        "水庫放流量/立方公尺": "1,529,820",
        "進流量減放流量/立方公尺": "759,000",
        "南勢溪流量/立方公尺": "8,131,320",
        "南北勢溪合計原水量/立方公尺": "9,661,140"
      },
      {
        "_id": 9,
        "_importdate": {
          "date": "2026-05-08 17:34:56.088753",
          "timezone_type": 3,
          "timezone": "Asia/Taipei"
        },
        "日期": "10月9日",
        "翡翠水庫日平均水位/公尺": "156.33",
        "水庫有效蓄水量/百萬立方公尺": "219.458",
        "集水區平均雨量/毫米": "11.8",
        "水庫進流量/立方公尺": "2,210,408",
        "水庫放流量/立方公尺": "1,527,408",
        "進流量減放流量/立方公尺": "683,000",
        "南勢溪流量/立方公尺": "11,721,600",
        "南北勢溪合計原水量/立方公尺": "13,249,008"
      },
      {
        "_id": 10,
        "_importdate": {
          "date": "2026-05-08 17:34:56.089236",
          "timezone_type": 3,
          "timezone": "Asia/Taipei"
        },
        "日期": "10月10日",
        "翡翠水庫日平均水位/公尺": "156.47",
        "水庫有效蓄水量/百萬立方公尺": "220.53",
        "集水區平均雨量/毫米": "32.9",
        "水庫進流量/立方公尺": "3,433,480",
        "水庫放流量/立方公尺": "1,527,480",
        "進流量減放流量/立方公尺": "1,906,000",
        "南勢溪流量/立方公尺": "5,724,000",
        "南北勢溪合計原水量/立方公尺": "7,251,480"
      },
      {
        "_id": 11,
        "_importdate": {
          "date": "2026-05-08 17:34:56.089704",
          "timezone_type": 3,
          "timezone": "Asia/Taipei"
        },
        "日期": "10月11日",
        "翡翠水庫日平均水位/公尺": "156.86",
        "水庫有效蓄水量/百萬立方公尺": "223.602",
        "集水區平均雨量/毫米": "38.2",
        "水庫進流量/立方公尺": "5,682,972",
        "水庫放流量/立方公尺": "1,530,972",
        "進流量減放流量/立方公尺": "4,152,000",
        "南勢溪流量/立方公尺": "9,590,400",
        "南北勢溪合計原水量/立方公尺": "11,121,372"
      },
      {
        "_id": 12,
        "_importdate": {
          "date": "2026-05-08 17:34:56.090190",
          "timezone_type": 3,
          "timezone": "Asia/Taipei"
        },
        "日期": "10月12日",
        "翡翠水庫日平均水位/公尺": "157.94",
        "水庫有效蓄水量/百萬立方公尺": "232.29",
        "集水區平均雨量/毫米": "84.1",
        "水庫進流量/立方公尺": "16,067,772",
        "水庫放流量/立方公尺": "1,505,772",
        "進流量減放流量/立方公尺": "14,562,000",
        "南勢溪流量/立方公尺": "22,118,400",
        "南北勢溪合計原水量/立方公尺": "23,624,172"
      },
      {
        "_id": 13,
        "_importdate": {
          "date": "2026-05-08 17:34:56.090671",
          "timezone_type": 3,
          "timezone": "Asia/Taipei"
        },
        "日期": "10月13日",
        "翡翠水庫日平均水位/公尺": "159.84",
        "水庫有效蓄水量/百萬立方公尺": "247.823",
        "集水區平均雨量/毫米": "151",
        "水庫進流量/立方公尺": "23,499,512",
        "水庫放流量/立方公尺": "1,477,512",
        "進流量減放流量/立方公尺": "22,022,000",
        "南勢溪流量/立方公尺": "23,673,600",
        "南北勢溪合計原水量/立方公尺": "25,151,112"
      },
      {
        "_id": 14,
        "_importdate": {
          "date": "2026-05-08 17:34:56.091252",
          "timezone_type": 3,
          "timezone": "Asia/Taipei"
        },
        "日期": "10月14日",
        "翡翠水庫日平均水位/公尺": "164.92",
        "水庫有效蓄水量/百萬立方公尺": "290.75",
        "集水區平均雨量/毫米": "155.5",
        "水庫進流量/立方公尺": "54,657,640",
        "水庫放流量/立方公尺": "7,145,640",
        "進流量減放流量/立方公尺": "47,512,000",
        "南勢溪流量/立方公尺": "78,624,000",
        "南北勢溪合計原水量/立方公尺": "85,769,640"
      },
      {
        "_id": 15,
        "_importdate": {
          "date": "2026-05-08 17:34:56.091825",
          "timezone_type": 3,
          "timezone": "Asia/Taipei"
        },
        "日期": "10月15日",
        "翡翠水庫日平均水位/公尺": "168.01",
        "水庫有效蓄水量/百萬立方公尺": "316.968",
        "集水區平均雨量/毫米": "60.4",
        "水庫進流量/立方公尺": "35,844,708",
        "水庫放流量/立方公尺": "27,264,708",
        "進流量減放流量/立方公尺": "8,580,000",
        "南勢溪流量/立方公尺": "31,665,600",
        "南北勢溪合計原水量/立方公尺": "58,930,308"
      },
      {
        "_id": 16,
        "_importdate": {
          "date": "2026-05-08 17:34:56.092278",
          "timezone_type": 3,
          "timezone": "Asia/Taipei"
        },
        "日期": "10月16日",
        "翡翠水庫日平均水位/公尺": "167.81",
        "水庫有效蓄水量/百萬立方公尺": "314.995",
        "集水區平均雨量/毫米": "0.9",
        "水庫進流量/立方公尺": "11,888,404",
        "水庫放流量/立方公尺": "16,102,404",
        "進流量減放流量/立方公尺": "-4,214,000",
        "南勢溪流量/立方公尺": "21,664,800",
        "南北勢溪合計原水量/立方公尺": "37,767,204"
      },
      {
        "_id": 17,
        "_importdate": {
          "date": "2026-05-08 17:34:56.092735",
          "timezone_type": 3,
          "timezone": "Asia/Taipei"
        },
        "日期": "10月17日",
        "翡翠水庫日平均水位/公尺": "167.65",
        "水庫有效蓄水量/百萬立方公尺": "313.582",
        "集水區平均雨量/毫米": "8.8",
        "水庫進流量/立方公尺": "5,152,728",
        "水庫放流量/立方公尺": "6,670,728",
        "進流量減放流量/立方公尺": "-1,518,000",
        "南勢溪流量/立方公尺": "13,240,800",
        "南北勢溪合計原水量/立方公尺": "19,911,528"
      },
      {
        "_id": 18,
        "_importdate": {
          "date": "2026-05-08 17:34:56.093194",
          "timezone_type": 3,
          "timezone": "Asia/Taipei"
        },
        "日期": "10月18日",
        "翡翠水庫日平均水位/公尺": "167.4",
        "水庫有效蓄水量/百萬立方公尺": "311.382",
        "集水區平均雨量/毫米": "20.7",
        "水庫進流量/立方公尺": "4,368,912",
        "水庫放流量/立方公尺": "6,684,912",
        "進流量減放流量/立方公尺": "-2,316,000",
        "南勢溪流量/立方公尺": "9,547,200",
        "南北勢溪合計原水量/立方公尺": "16,232,112"
      },
      {
        "_id": 19,
        "_importdate": {
          "date": "2026-05-08 17:34:56.093777",
          "timezone_type": 3,
          "timezone": "Asia/Taipei"
        },
        "日期": "10月19日",
        "翡翠水庫日平均水位/公尺": "167.24",
        "水庫有效蓄水量/百萬立方公尺": "309.991",
        "集水區平均雨量/毫米": "31.1",
        "水庫進流量/立方公尺": "6,512,924",
        "水庫放流量/立方公尺": "6,690,924",
        "進流量減放流量/立方公尺": "-178,000",
        "南勢溪流量/立方公尺": "8,488,800",
        "南北勢溪合計原水量/立方公尺": "15,179,724"
      },
      {
        "_id": 20,
        "_importdate": {
          "date": "2026-05-08 17:34:56.094258",
          "timezone_type": 3,
          "timezone": "Asia/Taipei"
        },
        "日期": "10月20日",
        "翡翠水庫日平均水位/公尺": "167.34",
        "水庫有效蓄水量/百萬立方公尺": "310.952",
        "集水區平均雨量/毫米": "31.3",
        "水庫進流量/立方公尺": "8,197,400",
        "水庫放流量/立方公尺": "6,683,400",
        "進流量減放流量/立方公尺": "1,514,000",
        "南勢溪流量/立方公尺": "9,003,600",
        "南北勢溪合計原水量/立方公尺": "15,687,000"
      },
      {
        "_id": 21,
        "_importdate": {
          "date": "2026-05-08 17:34:56.094724",
          "timezone_type": 3,
          "timezone": "Asia/Taipei"
        },
        "日期": "10月21日",
        "翡翠水庫日平均水位/公尺": "167.51",
        "水庫有效蓄水量/百萬立方公尺": "312.433",
        "集水區平均雨量/毫米": "8.2",
        "水庫進流量/立方公尺": "7,476,392",
        "水庫放流量/立方公尺": "6,673,392",
        "進流量減放流量/立方公尺": "803,000",
        "南勢溪流量/立方公尺": "9,378,000",
        "南北勢溪合計原水量/立方公尺": "16,051,392"
      },
      {
        "_id": 22,
        "_importdate": {
          "date": "2026-05-08 17:34:56.095203",
          "timezone_type": 3,
          "timezone": "Asia/Taipei"
        },
        "日期": "10月22日",
        "翡翠水庫日平均水位/公尺": "167.43",
        "水庫有效蓄水量/百萬立方公尺": "311.605",
        "集水區平均雨量/毫米": "0.2",
        "水庫進流量/立方公尺": "4,630,008",
        "水庫放流量/立方公尺": "6,679,008",
        "進流量減放流量/立方公尺": "-2,049,000",
        "南勢溪流量/立方公尺": "6,998,400",
        "南北勢溪合計原水量/立方公尺": "13,677,408"
      },
      {
        "_id": 23,
        "_importdate": {
          "date": "2026-05-08 17:34:56.095684",
          "timezone_type": 3,
          "timezone": "Asia/Taipei"
        },
        "日期": "10月23日",
        "翡翠水庫日平均水位/公尺": "167.1",
        "水庫有效蓄水量/百萬立方公尺": "308.681",
        "集水區平均雨量/毫米": "0.3",
        "水庫進流量/立方公尺": "3,225,376",
        "水庫放流量/立方公尺": "6,689,376",
        "進流量減放流量/立方公尺": "-3,464,000",
        "南勢溪流量/立方公尺": "5,680,800",
        "南北勢溪合計原水量/立方公尺": "12,370,176"
      },
      {
        "_id": 24,
        "_importdate": {
          "date": "2026-05-08 17:34:56.096159",
          "timezone_type": 3,
          "timezone": "Asia/Taipei"
        },
        "日期": "10月24日",
        "翡翠水庫日平均水位/公尺": "166.89",
        "水庫有效蓄水量/百萬立方公尺": "306.806",
        "集水區平均雨量/毫米": "2.6",
        "水庫進流量/立方公尺": "2,014,760",
        "水庫放流量/立方公尺": "3,254,760",
        "進流量減放流量/立方公尺": "-1,240,000",
        "南勢溪流量/立方公尺": "4,687,200",
        "南北勢溪合計原水量/立方公尺": "7,941,960"
      },
      {
        "_id": 25,
        "_importdate": {
          "date": "2026-05-08 17:34:56.096658",
          "timezone_type": 3,
          "timezone": "Asia/Taipei"
        },
        "日期": "10月25日",
        "翡翠水庫日平均水位/公尺": "166.77",
        "水庫有效蓄水量/百萬立方公尺": "305.791",
        "集水區平均雨量/毫米": "1.1",
        "水庫進流量/立方公尺": "1,655,708",
        "水庫放流量/立方公尺": "2,982,708",
        "進流量減放流量/立方公尺": "-1,327,000",
        "南勢溪流量/立方公尺": "3,866,400",
        "南北勢溪合計原水量/立方公尺": "6,849,108"
      },
      {
        "_id": 26,
        "_importdate": {
          "date": "2026-05-08 17:34:56.097147",
          "timezone_type": 3,
          "timezone": "Asia/Taipei"
        },
        "日期": "10月26日",
        "翡翠水庫日平均水位/公尺": "166.57",
        "水庫有效蓄水量/百萬立方公尺": "303.985",
        "集水區平均雨量/毫米": "0.1",
        "水庫進流量/立方公尺": "1,412,496",
        "水庫放流量/立方公尺": "3,266,496",
        "進流量減放流量/立方公尺": "-1,854,000",
        "南勢溪流量/立方公尺": "3,391,200",
        "南北勢溪合計原水量/立方公尺": "6,657,696"
      },
      {
        "_id": 27,
        "_importdate": {
          "date": "2026-05-08 17:34:56.097628",
          "timezone_type": 3,
          "timezone": "Asia/Taipei"
        },
        "日期": "10月27日",
        "翡翠水庫日平均水位/公尺": "166.36",
        "水庫有效蓄水量/百萬立方公尺": "302.117",
        "集水區平均雨量/毫米": "3.7",
        "水庫進流量/立方公尺": "1,420,312",
        "水庫放流量/立方公尺": "3,270,312",
        "進流量減放流量/立方公尺": "-1,850,000",
        "南勢溪流量/立方公尺": "3,031,200",
        "南北勢溪合計原水量/立方公尺": "6,301,512"
      },
      {
        "_id": 28,
        "_importdate": {
          "date": "2026-05-08 17:34:56.098125",
          "timezone_type": 3,
          "timezone": "Asia/Taipei"
        },
        "日期": "10月28日",
        "翡翠水庫日平均水位/公尺": "166.14",
        "水庫有效蓄水量/百萬立方公尺": "300.206",
        "集水區平均雨量/毫米": "9.3",
        "水庫進流量/立方公尺": "1,343,252",
        "水庫放流量/立方公尺": "3,276,252",
        "進流量減放流量/立方公尺": "-1,933,000",
        "南勢溪流量/立方公尺": "2,844,000",
        "南北勢溪合計原水量/立方公尺": "6,120,252"
      },
      {
        "_id": 29,
        "_importdate": {
          "date": "2026-05-08 17:34:56.098603",
          "timezone_type": 3,
          "timezone": "Asia/Taipei"
        },
        "日期": "10月29日",
        "翡翠水庫日平均水位/公尺": "165.92",
        "水庫有效蓄水量/百萬立方公尺": "298.26",
        "集水區平均雨量/毫米": "5.8",
        "水庫進流量/立方公尺": "1,269,188",
        "水庫放流量/立方公尺": "3,286,188",
        "進流量減放流量/立方公尺": "-2,017,000",
        "南勢溪流量/立方公尺": "2,609,280",
        "南北勢溪合計原水量/立方公尺": "5,895,468"
      },
      {
        "_id": 30,
        "_importdate": {
          "date": "2026-05-08 17:34:56.099077",
          "timezone_type": 3,
          "timezone": "Asia/Taipei"
        },
        "日期": "10月30日",
        "翡翠水庫日平均水位/公尺": "165.69",
        "水庫有效蓄水量/百萬立方公尺": "296.219",
        "集水區平均雨量/毫米": "4.1",
        "水庫進流量/立方公尺": "1,280,660",
        "水庫放流量/立方公尺": "3,291,660",
        "進流量減放流量/立方公尺": "-2,011,000",
        "南勢溪流量/立方公尺": "2,367,360",
        "南北勢溪合計原水量/立方公尺": "5,659,020"
      },
      {
        "_id": 31,
        "_importdate": {
          "date": "2026-05-08 17:34:56.099575",
          "timezone_type": 3,
          "timezone": "Asia/Taipei"
        },
        "日期": "10月31日",
        "翡翠水庫日平均水位/公尺": "165.45",
        "水庫有效蓄水量/百萬立方公尺": "294.123",
        "集水區平均雨量/毫米": "6.1",
        "水庫進流量/立方公尺": "1,207,392",
        "水庫放流量/立方公尺": "3,298,392",
        "進流量減放流量/立方公尺": "-2,091,000",
        "南勢溪流量/立方公尺": "2,203,200",
        "南北勢溪合計原水量/立方公尺": "5,501,592"
      }
    ]
  },
  "sourceEnvelope": {
    "result": {
      "limit": 1000,
      "offset": 0,
      "count": 31,
      "sort": "",
      "results": [
        {
          "_id": 1,
          "_importdate": {
            "date": "2026-05-08 17:34:56.076394",
            "timezone_type": 3,
            "timezone": "Asia/Taipei"
          },
          "日期": "10月1日",
          "翡翠水庫日平均水位/公尺": "156.37",
          "水庫有效蓄水量/百萬立方公尺": "219.7",
          "集水區平均雨量/毫米": "0.5",
          "水庫進流量/立方公尺": "1,015,180",
          "水庫放流量/立方公尺": "1,926,180",
          "進流量減放流量/立方公尺": "-911,000",
          "南勢溪流量/立方公尺": "1,200,960",
          "南北勢溪合計原水量/立方公尺": "3,127,140"
        },
        {
          "_id": 2,
          "_importdate": {
            "date": "2026-05-08 17:34:56.085106",
            "timezone_type": 3,
            "timezone": "Asia/Taipei"
          },
          "日期": "10月2日",
          "翡翠水庫日平均水位/公尺": "156.22",
          "水庫有效蓄水量/百萬立方公尺": "218.59",
          "集水區平均雨量/毫米": "0",
          "水庫進流量/立方公尺": "739,560",
          "水庫放流量/立方公尺": "1,951,560",
          "進流量減放流量/立方公尺": "-1,212,000",
          "南勢溪流量/立方公尺": "1,127,520",
          "南北勢溪合計原水量/立方公尺": "3,079,080"
        },
        {
          "_id": 3,
          "_importdate": {
            "date": "2026-05-08 17:34:56.085696",
            "timezone_type": 3,
            "timezone": "Asia/Taipei"
          },
          "日期": "10月3日",
          "翡翠水庫日平均水位/公尺": "156.05",
          "水庫有效蓄水量/百萬立方公尺": "217.257",
          "集水區平均雨量/毫米": "8.5",
          "水庫進流量/立方公尺": "664,992",
          "水庫放流量/立方公尺": "2,248,992",
          "進流量減放流量/立方公尺": "-1,584,000",
          "南勢溪流量/立方公尺": "1,092,240",
          "南北勢溪合計原水量/立方公尺": "3,341,232"
        },
        {
          "_id": 4,
          "_importdate": {
            "date": "2026-05-08 17:34:56.086217",
            "timezone_type": 3,
            "timezone": "Asia/Taipei"
          },
          "日期": "10月4日",
          "翡翠水庫日平均水位/公尺": "155.89",
          "水庫有效蓄水量/百萬立方公尺": "216.108",
          "集水區平均雨量/毫米": "32.6",
          "水庫進流量/立方公尺": "1,152,344",
          "水庫放流量/立方公尺": "1,528,344",
          "進流量減放流量/立方公尺": "-376,000",
          "南勢溪流量/立方公尺": "1,503,360",
          "南北勢溪合計原水量/立方公尺": "3,031,704"
        },
        {
          "_id": 5,
          "_importdate": {
            "date": "2026-05-08 17:34:56.086691",
            "timezone_type": 3,
            "timezone": "Asia/Taipei"
          },
          "日期": "10月5日",
          "翡翠水庫日平均水位/公尺": "155.9",
          "水庫有效蓄水量/百萬立方公尺": "216.186",
          "集水區平均雨量/毫米": "3.9",
          "水庫進流量/立方公尺": "1,830,064",
          "水庫放流量/立方公尺": "1,529,064",
          "進流量減放流量/立方公尺": "301,000",
          "南勢溪流量/立方公尺": "1,771,200",
          "南北勢溪合計原水量/立方公尺": "3,300,264"
        },
        {
          "_id": 6,
          "_importdate": {
            "date": "2026-05-08 17:34:56.087183",
            "timezone_type": 3,
            "timezone": "Asia/Taipei"
          },
          "日期": "10月6日",
          "翡翠水庫日平均水位/公尺": "155.9",
          "水庫有效蓄水量/百萬立方公尺": "216.18",
          "集水區平均雨量/毫米": "18.1",
          "水庫進流量/立方公尺": "1,380,252",
          "水庫放流量/立方公尺": "1,530,252",
          "進流量減放流量/立方公尺": "-150,000",
          "南勢溪流量/立方公尺": "1,743,120",
          "南北勢溪合計原水量/立方公尺": "3,273,372"
        },
        {
          "_id": 7,
          "_importdate": {
            "date": "2026-05-08 17:34:56.087747",
            "timezone_type": 3,
            "timezone": "Asia/Taipei"
          },
          "日期": "10月7日",
          "翡翠水庫日平均水位/公尺": "156.04",
          "水庫有效蓄水量/百萬立方公尺": "217.323",
          "集水區平均雨量/毫米": "12.7",
          "水庫進流量/立方公尺": "3,716,452",
          "水庫放流量/立方公尺": "1,528,452",
          "進流量減放流量/立方公尺": "2,188,000",
          "南勢溪流量/立方公尺": "3,348,360",
          "南北勢溪合計原水量/立方公尺": "4,876,812"
        },
        {
          "_id": 8,
          "_importdate": {
            "date": "2026-05-08 17:34:56.088234",
            "timezone_type": 3,
            "timezone": "Asia/Taipei"
          },
          "日期": "10月8日",
          "翡翠水庫日平均水位/公尺": "156.24",
          "水庫有效蓄水量/百萬立方公尺": "218.782",
          "集水區平均雨量/毫米": "10.7",
          "水庫進流量/立方公尺": "2,288,820",
          "水庫放流量/立方公尺": "1,529,820",
          "進流量減放流量/立方公尺": "759,000",
          "南勢溪流量/立方公尺": "8,131,320",
          "南北勢溪合計原水量/立方公尺": "9,661,140"
        },
        {
          "_id": 9,
          "_importdate": {
            "date": "2026-05-08 17:34:56.088753",
            "timezone_type": 3,
            "timezone": "Asia/Taipei"
          },
          "日期": "10月9日",
          "翡翠水庫日平均水位/公尺": "156.33",
          "水庫有效蓄水量/百萬立方公尺": "219.458",
          "集水區平均雨量/毫米": "11.8",
          "水庫進流量/立方公尺": "2,210,408",
          "水庫放流量/立方公尺": "1,527,408",
          "進流量減放流量/立方公尺": "683,000",
          "南勢溪流量/立方公尺": "11,721,600",
          "南北勢溪合計原水量/立方公尺": "13,249,008"
        },
        {
          "_id": 10,
          "_importdate": {
            "date": "2026-05-08 17:34:56.089236",
            "timezone_type": 3,
            "timezone": "Asia/Taipei"
          },
          "日期": "10月10日",
          "翡翠水庫日平均水位/公尺": "156.47",
          "水庫有效蓄水量/百萬立方公尺": "220.53",
          "集水區平均雨量/毫米": "32.9",
          "水庫進流量/立方公尺": "3,433,480",
          "水庫放流量/立方公尺": "1,527,480",
          "進流量減放流量/立方公尺": "1,906,000",
          "南勢溪流量/立方公尺": "5,724,000",
          "南北勢溪合計原水量/立方公尺": "7,251,480"
        },
        {
          "_id": 11,
          "_importdate": {
            "date": "2026-05-08 17:34:56.089704",
            "timezone_type": 3,
            "timezone": "Asia/Taipei"
          },
          "日期": "10月11日",
          "翡翠水庫日平均水位/公尺": "156.86",
          "水庫有效蓄水量/百萬立方公尺": "223.602",
          "集水區平均雨量/毫米": "38.2",
          "水庫進流量/立方公尺": "5,682,972",
          "水庫放流量/立方公尺": "1,530,972",
          "進流量減放流量/立方公尺": "4,152,000",
          "南勢溪流量/立方公尺": "9,590,400",
          "南北勢溪合計原水量/立方公尺": "11,121,372"
        },
        {
          "_id": 12,
          "_importdate": {
            "date": "2026-05-08 17:34:56.090190",
            "timezone_type": 3,
            "timezone": "Asia/Taipei"
          },
          "日期": "10月12日",
          "翡翠水庫日平均水位/公尺": "157.94",
          "水庫有效蓄水量/百萬立方公尺": "232.29",
          "集水區平均雨量/毫米": "84.1",
          "水庫進流量/立方公尺": "16,067,772",
          "水庫放流量/立方公尺": "1,505,772",
          "進流量減放流量/立方公尺": "14,562,000",
          "南勢溪流量/立方公尺": "22,118,400",
          "南北勢溪合計原水量/立方公尺": "23,624,172"
        },
        {
          "_id": 13,
          "_importdate": {
            "date": "2026-05-08 17:34:56.090671",
            "timezone_type": 3,
            "timezone": "Asia/Taipei"
          },
          "日期": "10月13日",
          "翡翠水庫日平均水位/公尺": "159.84",
          "水庫有效蓄水量/百萬立方公尺": "247.823",
          "集水區平均雨量/毫米": "151",
          "水庫進流量/立方公尺": "23,499,512",
          "水庫放流量/立方公尺": "1,477,512",
          "進流量減放流量/立方公尺": "22,022,000",
          "南勢溪流量/立方公尺": "23,673,600",
          "南北勢溪合計原水量/立方公尺": "25,151,112"
        },
        {
          "_id": 14,
          "_importdate": {
            "date": "2026-05-08 17:34:56.091252",
            "timezone_type": 3,
            "timezone": "Asia/Taipei"
          },
          "日期": "10月14日",
          "翡翠水庫日平均水位/公尺": "164.92",
          "水庫有效蓄水量/百萬立方公尺": "290.75",
          "集水區平均雨量/毫米": "155.5",
          "水庫進流量/立方公尺": "54,657,640",
          "水庫放流量/立方公尺": "7,145,640",
          "進流量減放流量/立方公尺": "47,512,000",
          "南勢溪流量/立方公尺": "78,624,000",
          "南北勢溪合計原水量/立方公尺": "85,769,640"
        },
        {
          "_id": 15,
          "_importdate": {
            "date": "2026-05-08 17:34:56.091825",
            "timezone_type": 3,
            "timezone": "Asia/Taipei"
          },
          "日期": "10月15日",
          "翡翠水庫日平均水位/公尺": "168.01",
          "水庫有效蓄水量/百萬立方公尺": "316.968",
          "集水區平均雨量/毫米": "60.4",
          "水庫進流量/立方公尺": "35,844,708",
          "水庫放流量/立方公尺": "27,264,708",
          "進流量減放流量/立方公尺": "8,580,000",
          "南勢溪流量/立方公尺": "31,665,600",
          "南北勢溪合計原水量/立方公尺": "58,930,308"
        },
        {
          "_id": 16,
          "_importdate": {
            "date": "2026-05-08 17:34:56.092278",
            "timezone_type": 3,
            "timezone": "Asia/Taipei"
          },
          "日期": "10月16日",
          "翡翠水庫日平均水位/公尺": "167.81",
          "水庫有效蓄水量/百萬立方公尺": "314.995",
          "集水區平均雨量/毫米": "0.9",
          "水庫進流量/立方公尺": "11,888,404",
          "水庫放流量/立方公尺": "16,102,404",
          "進流量減放流量/立方公尺": "-4,214,000",
          "南勢溪流量/立方公尺": "21,664,800",
          "南北勢溪合計原水量/立方公尺": "37,767,204"
        },
        {
          "_id": 17,
          "_importdate": {
            "date": "2026-05-08 17:34:56.092735",
            "timezone_type": 3,
            "timezone": "Asia/Taipei"
          },
          "日期": "10月17日",
          "翡翠水庫日平均水位/公尺": "167.65",
          "水庫有效蓄水量/百萬立方公尺": "313.582",
          "集水區平均雨量/毫米": "8.8",
          "水庫進流量/立方公尺": "5,152,728",
          "水庫放流量/立方公尺": "6,670,728",
          "進流量減放流量/立方公尺": "-1,518,000",
          "南勢溪流量/立方公尺": "13,240,800",
          "南北勢溪合計原水量/立方公尺": "19,911,528"
        },
        {
          "_id": 18,
          "_importdate": {
            "date": "2026-05-08 17:34:56.093194",
            "timezone_type": 3,
            "timezone": "Asia/Taipei"
          },
          "日期": "10月18日",
          "翡翠水庫日平均水位/公尺": "167.4",
          "水庫有效蓄水量/百萬立方公尺": "311.382",
          "集水區平均雨量/毫米": "20.7",
          "水庫進流量/立方公尺": "4,368,912",
          "水庫放流量/立方公尺": "6,684,912",
          "進流量減放流量/立方公尺": "-2,316,000",
          "南勢溪流量/立方公尺": "9,547,200",
          "南北勢溪合計原水量/立方公尺": "16,232,112"
        },
        {
          "_id": 19,
          "_importdate": {
            "date": "2026-05-08 17:34:56.093777",
            "timezone_type": 3,
            "timezone": "Asia/Taipei"
          },
          "日期": "10月19日",
          "翡翠水庫日平均水位/公尺": "167.24",
          "水庫有效蓄水量/百萬立方公尺": "309.991",
          "集水區平均雨量/毫米": "31.1",
          "水庫進流量/立方公尺": "6,512,924",
          "水庫放流量/立方公尺": "6,690,924",
          "進流量減放流量/立方公尺": "-178,000",
          "南勢溪流量/立方公尺": "8,488,800",
          "南北勢溪合計原水量/立方公尺": "15,179,724"
        },
        {
          "_id": 20,
          "_importdate": {
            "date": "2026-05-08 17:34:56.094258",
            "timezone_type": 3,
            "timezone": "Asia/Taipei"
          },
          "日期": "10月20日",
          "翡翠水庫日平均水位/公尺": "167.34",
          "水庫有效蓄水量/百萬立方公尺": "310.952",
          "集水區平均雨量/毫米": "31.3",
          "水庫進流量/立方公尺": "8,197,400",
          "水庫放流量/立方公尺": "6,683,400",
          "進流量減放流量/立方公尺": "1,514,000",
          "南勢溪流量/立方公尺": "9,003,600",
          "南北勢溪合計原水量/立方公尺": "15,687,000"
        },
        {
          "_id": 21,
          "_importdate": {
            "date": "2026-05-08 17:34:56.094724",
            "timezone_type": 3,
            "timezone": "Asia/Taipei"
          },
          "日期": "10月21日",
          "翡翠水庫日平均水位/公尺": "167.51",
          "水庫有效蓄水量/百萬立方公尺": "312.433",
          "集水區平均雨量/毫米": "8.2",
          "水庫進流量/立方公尺": "7,476,392",
          "水庫放流量/立方公尺": "6,673,392",
          "進流量減放流量/立方公尺": "803,000",
          "南勢溪流量/立方公尺": "9,378,000",
          "南北勢溪合計原水量/立方公尺": "16,051,392"
        },
        {
          "_id": 22,
          "_importdate": {
            "date": "2026-05-08 17:34:56.095203",
            "timezone_type": 3,
            "timezone": "Asia/Taipei"
          },
          "日期": "10月22日",
          "翡翠水庫日平均水位/公尺": "167.43",
          "水庫有效蓄水量/百萬立方公尺": "311.605",
          "集水區平均雨量/毫米": "0.2",
          "水庫進流量/立方公尺": "4,630,008",
          "水庫放流量/立方公尺": "6,679,008",
          "進流量減放流量/立方公尺": "-2,049,000",
          "南勢溪流量/立方公尺": "6,998,400",
          "南北勢溪合計原水量/立方公尺": "13,677,408"
        },
        {
          "_id": 23,
          "_importdate": {
            "date": "2026-05-08 17:34:56.095684",
            "timezone_type": 3,
            "timezone": "Asia/Taipei"
          },
          "日期": "10月23日",
          "翡翠水庫日平均水位/公尺": "167.1",
          "水庫有效蓄水量/百萬立方公尺": "308.681",
          "集水區平均雨量/毫米": "0.3",
          "水庫進流量/立方公尺": "3,225,376",
          "水庫放流量/立方公尺": "6,689,376",
          "進流量減放流量/立方公尺": "-3,464,000",
          "南勢溪流量/立方公尺": "5,680,800",
          "南北勢溪合計原水量/立方公尺": "12,370,176"
        },
        {
          "_id": 24,
          "_importdate": {
            "date": "2026-05-08 17:34:56.096159",
            "timezone_type": 3,
            "timezone": "Asia/Taipei"
          },
          "日期": "10月24日",
          "翡翠水庫日平均水位/公尺": "166.89",
          "水庫有效蓄水量/百萬立方公尺": "306.806",
          "集水區平均雨量/毫米": "2.6",
          "水庫進流量/立方公尺": "2,014,760",
          "水庫放流量/立方公尺": "3,254,760",
          "進流量減放流量/立方公尺": "-1,240,000",
          "南勢溪流量/立方公尺": "4,687,200",
          "南北勢溪合計原水量/立方公尺": "7,941,960"
        },
        {
          "_id": 25,
          "_importdate": {
            "date": "2026-05-08 17:34:56.096658",
            "timezone_type": 3,
            "timezone": "Asia/Taipei"
          },
          "日期": "10月25日",
          "翡翠水庫日平均水位/公尺": "166.77",
          "水庫有效蓄水量/百萬立方公尺": "305.791",
          "集水區平均雨量/毫米": "1.1",
          "水庫進流量/立方公尺": "1,655,708",
          "水庫放流量/立方公尺": "2,982,708",
          "進流量減放流量/立方公尺": "-1,327,000",
          "南勢溪流量/立方公尺": "3,866,400",
          "南北勢溪合計原水量/立方公尺": "6,849,108"
        },
        {
          "_id": 26,
          "_importdate": {
            "date": "2026-05-08 17:34:56.097147",
            "timezone_type": 3,
            "timezone": "Asia/Taipei"
          },
          "日期": "10月26日",
          "翡翠水庫日平均水位/公尺": "166.57",
          "水庫有效蓄水量/百萬立方公尺": "303.985",
          "集水區平均雨量/毫米": "0.1",
          "水庫進流量/立方公尺": "1,412,496",
          "水庫放流量/立方公尺": "3,266,496",
          "進流量減放流量/立方公尺": "-1,854,000",
          "南勢溪流量/立方公尺": "3,391,200",
          "南北勢溪合計原水量/立方公尺": "6,657,696"
        },
        {
          "_id": 27,
          "_importdate": {
            "date": "2026-05-08 17:34:56.097628",
            "timezone_type": 3,
            "timezone": "Asia/Taipei"
          },
          "日期": "10月27日",
          "翡翠水庫日平均水位/公尺": "166.36",
          "水庫有效蓄水量/百萬立方公尺": "302.117",
          "集水區平均雨量/毫米": "3.7",
          "水庫進流量/立方公尺": "1,420,312",
          "水庫放流量/立方公尺": "3,270,312",
          "進流量減放流量/立方公尺": "-1,850,000",
          "南勢溪流量/立方公尺": "3,031,200",
          "南北勢溪合計原水量/立方公尺": "6,301,512"
        },
        {
          "_id": 28,
          "_importdate": {
            "date": "2026-05-08 17:34:56.098125",
            "timezone_type": 3,
            "timezone": "Asia/Taipei"
          },
          "日期": "10月28日",
          "翡翠水庫日平均水位/公尺": "166.14",
          "水庫有效蓄水量/百萬立方公尺": "300.206",
          "集水區平均雨量/毫米": "9.3",
          "水庫進流量/立方公尺": "1,343,252",
          "水庫放流量/立方公尺": "3,276,252",
          "進流量減放流量/立方公尺": "-1,933,000",
          "南勢溪流量/立方公尺": "2,844,000",
          "南北勢溪合計原水量/立方公尺": "6,120,252"
        },
        {
          "_id": 29,
          "_importdate": {
            "date": "2026-05-08 17:34:56.098603",
            "timezone_type": 3,
            "timezone": "Asia/Taipei"
          },
          "日期": "10月29日",
          "翡翠水庫日平均水位/公尺": "165.92",
          "水庫有效蓄水量/百萬立方公尺": "298.26",
          "集水區平均雨量/毫米": "5.8",
          "水庫進流量/立方公尺": "1,269,188",
          "水庫放流量/立方公尺": "3,286,188",
          "進流量減放流量/立方公尺": "-2,017,000",
          "南勢溪流量/立方公尺": "2,609,280",
          "南北勢溪合計原水量/立方公尺": "5,895,468"
        },
        {
          "_id": 30,
          "_importdate": {
            "date": "2026-05-08 17:34:56.099077",
            "timezone_type": 3,
            "timezone": "Asia/Taipei"
          },
          "日期": "10月30日",
          "翡翠水庫日平均水位/公尺": "165.69",
          "水庫有效蓄水量/百萬立方公尺": "296.219",
          "集水區平均雨量/毫米": "4.1",
          "水庫進流量/立方公尺": "1,280,660",
          "水庫放流量/立方公尺": "3,291,660",
          "進流量減放流量/立方公尺": "-2,011,000",
          "南勢溪流量/立方公尺": "2,367,360",
          "南北勢溪合計原水量/立方公尺": "5,659,020"
        },
        {
          "_id": 31,
          "_importdate": {
            "date": "2026-05-08 17:34:56.099575",
            "timezone_type": 3,
            "timezone": "Asia/Taipei"
          },
          "日期": "10月31日",
          "翡翠水庫日平均水位/公尺": "165.45",
          "水庫有效蓄水量/百萬立方公尺": "294.123",
          "集水區平均雨量/毫米": "6.1",
          "水庫進流量/立方公尺": "1,207,392",
          "水庫放流量/立方公尺": "3,298,392",
          "進流量減放流量/立方公尺": "-2,091,000",
          "南勢溪流量/立方公尺": "2,203,200",
          "南北勢溪合計原水量/立方公尺": "5,501,592"
        }
      ]
    }
  }
}
